byteprint.py
byteprint-1.2.7.1.dist-info/METADATA
byteprint-1.2.7.1.dist-info/WHEEL
byteprint-1.2.7.1.dist-info/top_level.txt
byteprint-1.2.7.1.dist-info/RECORD
