Metadata-Version: 2.4
Name: byteprint
Version: 1.2.7.1
Summary: 字节跳动风格延迟逐元素打印库，支持字符串/容器，毫秒/秒模式切换 | ByteDance-style delayed element-wise printing library
Author: nousername
Author-email: 2467906561@qq.com
License: MIT
Keywords: print,delay,byte dance,延迟打印,容器打印,打印
Requires-Python: >=3.6
